LICENSE.TXT
MANIFEST.in
ip2trace.py
readme.md
setup.cfg
IP2Trace.egg-info/PKG-INFO
IP2Trace.egg-info/SOURCES.txt
IP2Trace.egg-info/dependency_links.txt
IP2Trace.egg-info/entry_points.txt
IP2Trace.egg-info/requires.txt
IP2Trace.egg-info/top_level.txt
data/IP2LOCATION-LITE-DB1.IPV6.BIN
IP2Trace-3.2.2.dist-info/LICENSE.TXT
IP2Trace-3.2.2.dist-info/METADATA
IP2Trace-3.2.2.dist-info/WHEEL
IP2Trace-3.2.2.dist-info/entry_points.txt
IP2Trace-3.2.2.dist-info/top_level.txt
IP2Trace-3.2.2.dist-info/RECORD
